kashgari/__init__.py
kashgari/callbacks.py
kashgari/corpus.py
kashgari/macros.py
kashgari/migeration.py
kashgari/utils.py
kashgari/version.py
kashgari/embeddings/__init__.py
kashgari/embeddings/bare_embedding.py
kashgari/embeddings/base_embedding.py
kashgari/embeddings/bert_embedding.py
kashgari/embeddings/gpt_2_embedding.py
kashgari/embeddings/numeric_feature_embedding.py
kashgari/embeddings/stacked_embedding.py
kashgari/embeddings/word_embedding.py
kashgari/layers/__init__.py
kashgari/layers/att_wgt_avg_layer.py
kashgari/layers/crf.py
kashgari/layers/kmax_pool_layer.py
kashgari/layers/non_masking_layer.py
kashgari/processors/__init__.py
kashgari/processors/base_processor.py
kashgari/processors/classification_processor.py
kashgari/processors/labeling_processor.py
kashgari/tasks/__init__.py
kashgari/tasks/base_model.py
kashgari/tasks/classification/__init__.py
kashgari/tasks/classification/base_model.py
kashgari/tasks/classification/dpcnn_model.py
kashgari/tasks/classification/models.py
kashgari/tasks/labeling/__init__.py
kashgari/tasks/labeling/base_model.py
kashgari/tasks/labeling/experimental.py
kashgari/tasks/labeling/models.py
tests/classification/__init__.py
tests/classification/test_avcnn.py
tests/classification/test_avrnn_model.py
tests/classification/test_bi_gru.py
tests/classification/test_bi_lstm.py
tests/classification/test_cnn.py
tests/classification/test_cnn_gru.py
tests/classification/test_cnn_lstm.py
tests/classification/test_dpcnn.py
tests/classification/test_dropout_avrnn.py
tests/classification/test_dropout_bigru.py
tests/classification/test_kmax_cnn.py
tests/classification/test_r_cnn.py
tests/embedding/__init__.py
tests/embedding/test_bare_embedding.py
tests/embedding/test_bert_embedding.py
tests/embedding/test_gpt2_embedding.py
tests/embedding/test_numeric_features_embedding.py
tests/embedding/test_stacked_embedding.py
tests/embedding/test_word_embedding.py
tests/labeling/__init__.py
tests/labeling/test_bi_gru_crf_model.py
kashgari_tf-0.5.5.dist-info/LICENSE
kashgari_tf-0.5.5.dist-info/METADATA
kashgari_tf-0.5.5.dist-info/WHEEL
kashgari_tf-0.5.5.dist-info/top_level.txt
kashgari_tf-0.5.5.dist-info/RECORD
