Metadata-Version: 2.1
Name: kashgari-tf
Version: 0.5.5
Summary: Simple, Keras-powered multilingual NLP framework, allows you to build your models in 5 minutes for named entity recognition (NER), part-of-speech tagging (PoS) and text classification tasks. Includes BERT, GPT-2 and word2vec embedding.
Home-page: https://github.com/BrikerMan/Kashgari
Author: BrikerMan
Author-email: eliyar917@gmail.com
License: Apache License 2.0
Platform: UNKNOWN
Classifier: License :: OSI Approved :: Apache Software License
Classifier: Programming Language :: Python :: 3.6
Classifier: Programming Language :: Python :: Implementation :: CPython
Classifier: Programming Language :: Python :: Implementation :: PyPy
Requires-Python: >3.6
Requires-Dist: numpy (==1.16.4)
Requires-Dist: scikit-learn (>=0.21.1)
Requires-Dist: h5py
Requires-Dist: keras-bert (>=0.50.0)
Requires-Dist: keras-gpt-2 (>=0.8.0)
Requires-Dist: gensim (>=3.5.0)
Requires-Dist: seqeval (==0.0.10)
Requires-Dist: pandas (>=0.23.0)
